{
  "spot": [
    {
      "isActive": false,
      "area": "北海道",
      "star": 5,
      "hasToilet": false,
      "hasRoof": false,
      "hasBench": false,
      "id": 1
    }
  ],
  "config": {
    "region": [
      {
        "label": "北海道",
        "key": "北海道",
        "value": false
      },
      {
        "label": "東北",
        "key": "東北",
        "value": false
      },
      {
        "label": "関東",
        "key": "関東",
        "value": false
      },
      {
        "label": "北陸・甲信越",
        "key": "北陸・甲信越",
        "value": false
      },
      {
        "label": "東海",
        "key": "東海",
        "value": false
      },
      {
        "label": "近畿",
        "key": "近畿",
        "value": false
      },
      {
        "label": "中国",
        "key": "中国",
        "value": false
      },
      {
        "label": "四国",
        "key": "四国",
        "value": false
      },
      {
        "label": "九州・沖縄",
        "key": "九州・沖縄",
        "value": false
      }
    ],
    "attribute": [
      {
        "label": "ベンチがある",
        "key": "hasBench",
        "value": false
      },
      {
        "label": "屋根がある",
        "key": "hasRoof",
        "value": false
      },
      {
        "label": "トイレがある",
        "key": "hasToilet",
        "value": false
      }
    ]
  },
  "nowLocation": [
    {
      "data": [],
      "lat": 35.645843,
      "lng": 139.704582,
      "alt": 0,
      "accLatlng": 0,
      "heading": 0
    }
  ]
}